LICENSE
MANIFEST.in
README.rst
requirements.txt
s3file.py
setup.py
tests.py
python_s3file.egg-info/PKG-INFO
python_s3file.egg-info/SOURCES.txt
python_s3file.egg-info/dependency_links.txt
python_s3file.egg-info/requires.txt
python_s3file.egg-info/top_level.txt