Metadata-Version: 1.1
Name: python-s3file
Version: 1.3
Summary: Read and write to Amazon S3 using a file-like object
Home-page: http://github.com/jcarbaugh/python-s3file/
Author: Jeremy Carbaugh
Author-email: jcarbaugh@gmail.com
License: BSD
Platform: any
Classifier: Development Status :: 4 - Beta
Classifier: Intended Audience :: Developers
Classifier: License :: OSI Approved :: BSD License
Classifier: Natural Language :: English
Classifier: Operating System :: OS Independent
Classifier: Programming Language :: Python
Classifier: Topic :: Software Development :: Libraries :: Python Modules
